{
    "idSave": 323,
    "isFirstSession": false,
    "language": "ru",
    "promptDone": false,
    "money": 1,
    "newPlayerName": "Hello!",
    "openLevels": [
        false,
        false,
        false
    ],
    "allMoney": 15671.0,
    "moneyInSecond": 51.0,
    "moneyClick": 2.0,
    "bossIndex": 2,
    "level": 2,
    "levelProgress": 67.0,
    "shopSlot": {
        "instanceID": 25958
    },
    "backCost": [
        0,
        0,
        50000,
        200000,
        1000000,
        10000000,
        500000000,
        2000000000
    ]
}